hdmf_ai/__init__.py
hdmf_ai/results_table.py
hdmf_ai/schema/namespace.yaml
hdmf_ai/schema/results_table.yaml
hdmf_ai-0.2.0.dist-info/LICENSE
hdmf_ai-0.2.0.dist-info/METADATA
hdmf_ai-0.2.0.dist-info/WHEEL
hdmf_ai-0.2.0.dist-info/top_level.txt
hdmf_ai-0.2.0.dist-info/RECORD
