Metadata-Version: 2.1
Name: hdmf_ai
Version: 0.2.0
Summary: A schema and API for storing the results from AI/ML workflows
Author-email: Ryan Ly <rly@lbl.gov>, Andrew Tritt <ajtritt@lbl.gov>
License: BSD-3-Clause-LBNL
Project-URL: Homepage, https://github.com/hdmf-dev/hdmf-ai
Project-URL: Bug Tracker, https://github.com/hdmf-dev/hdmf-ai/issues
Keywords: python,cross-platform,open-data,data-format,open-source,open-science,reproducible-research,artificial-intelligence,machine-learning,data-standards
Classifier: Programming Language :: Python
Classifier: Programming Language :: Python :: 3.7
Classifier: Programming Language :: Python :: 3.8
Classifier: Programming Language :: Python :: 3.9
Classifier: Programming Language :: Python :: 3.10
Classifier: Programming Language :: Python :: 3.11
Classifier: Programming Language :: Python :: 3.12
Classifier: License :: OSI Approved :: BSD License
Classifier: Development Status :: 4 - Beta
Classifier: Operating System :: OS Independent
Classifier: Intended Audience :: Developers
Classifier: Intended Audience :: Science/Research
Classifier: Topic :: Scientific/Engineering :: Medical Science Apps.
Requires-Python: >=3.7
License-File: LICENSE
Requires-Dist: hdmf >=3.5.1
Requires-Dist: numpy >=1.21
Requires-Dist: scikit-learn >=1
